common_utils_pkg/Model.py
common_utils_pkg/ModelInterface.py
common_utils_pkg/__init__.py
common_utils_pkg/database.py
se4ai_group4_common_utils-0.3.7.dist-info/METADATA
se4ai_group4_common_utils-0.3.7.dist-info/WHEEL
se4ai_group4_common_utils-0.3.7.dist-info/top_level.txt
se4ai_group4_common_utils-0.3.7.dist-info/RECORD
