Metadata-Version: 2.1
Name: se4ai-group4-common-utils
Version: 0.3.7
Summary: A package for common utility functions that our project needs
Home-page: https://github.com/cmu-seai/group-project-se4ai-group-4
Author: Daniel Biales
Author-email: dbiales@andrew.cmu.edu
License: UNKNOWN
Platform: UNKNOWN
Classifier: Programming Language :: Python :: 3
Classifier: License :: OSI Approved :: MIT License
Classifier: Operating System :: OS Independent
Requires-Python: >=3.6
Requires-Dist: boto3
Requires-Dist: psycopg2-binary
Requires-Dist: sqlalchemy
Requires-Dist: surprise
Requires-Dist: wheel
